{
  "dependencies": [
    {
      "name": "discord_rpc",
      "type": "git",
      "ref": "master",
      "url": "https://github.com/Aidan63/linc_discord-rpc"
    },
    {
      "name": "linc_luajit",
      "type": "git",
      "ref": "main",
      "url": "https://github.com/Prohack101010/linc_luajit-extended"
    },
    {
      "name": "extension-androidtools",
      "type": "git",
      "ref": "6c8818a722499ffc93214e95110d560aa49f0e38",
      "url": "https://github.com/MAJigsaw77/extension-androidtools"
    },
    {
      "name": "flixel",
      "type": "git",
      "ref": "dev",
      "url": "https://github.com/Prohack101010/flixel"
    },
    {
      "name": "flixel-addons",
      "type": "haxelib",
      "version": "2.11.0"
    },
    {
      "name": "flixel-ui",
      "type": "haxelib",
      "version": "2.4.0"
    },
    {
      "name": "hscript",
      "type": "haxelib",
      "version": "2.4.0"
    },
    {
      "name": "hxCodec",
      "type": "haxelib",
      "version": "2.5.1"
    },
    {
      "name": "hxcpp",
      "type": "git",
      "ref": "stable",
      "url": "https://github.com/Prohack101010/hxcpp-extended.git"
    },
    {
      "name": "lime",
      "type": "git",
      "ref": "main",
      "url": "https://github.com/Prohack101010/lime-0.6.3-ex.git"
    },
    {
      "name": "openfl",
      "type": "haxelib",
      "version": "9.1.0"
    }
  ]
}